<?xml version="1.0" encoding="UTF-8"?>
<alpino_ds version="1.3">
  <node begin="0" cat="top" end="14" id="0" rel="top">
    <node begin="0" cat="smain" end="13" id="1" rel="--">
      <node begin="0" cat="np" end="2" id="2" rel="su">
        <node begin="0" buiging="met-e" end="1" id="3" lemma="deze" naamval="stan" npagr="rest" pdtype="det" pos="det" positie="prenom" postag="VNW(aanw,det,stan,prenom,met-e,rest)" pt="vnw" rel="det" root="deze" vwtype="aanw" word="Deze"/>
        <node begin="1" end="2" genus="zijd" getal="ev" graad="basis" id="4" lemma="wet" naamval="stan" ntype="soort" pos="noun" postag="N(soort,ev,basis,zijd,stan)" pt="n" rel="hd" root="wet" word="wet"/>
      </node>
      <node begin="2" end="3" id="5" lemma="regelen" pos="verb" postag="WW(pv,tgw,met-t)" pt="ww" pvagr="met-t" pvtijd="tgw" rel="hd" root="regel" word="regelt" wvorm="pv"/>
      <node begin="3" cat="np" end="13" id="6" rel="obj1">
        <node begin="3" end="4" id="7" lemma="een" lwtype="onbep" naamval="stan" npagr="agr" pos="det" postag="LID(onbep,stan,agr)" pt="lid" rel="det" root="een" word="een"/>
        <node begin="4" end="5" genus="zijd" getal="ev" graad="basis" id="8" lemma="aangelegenheid" naamval="stan" ntype="soort" pos="noun" postag="N(soort,ev,basis,zijd,stan)" pt="n" rel="hd" root="aangelegenheid" word="aangelegenheid"/>
        <node begin="5" cat="cp" end="13" id="9" rel="mod">
          <node begin="5" conjtype="onder" end="6" id="10" lemma="als" pos="comp" postag="VG(onder)" pt="vg" rel="cmp" root="als" word="als"/>
          <node begin="6" cat="ppart" end="13" id="11" rel="body">
            <node begin="6" buiging="zonder" end="7" id="12" lemma="bedoelen" pos="adj" positie="vrij" postag="WW(vd,vrij,zonder)" pt="ww" rel="hd" root="bedoeld" word="bedoeld" wvorm="vd"/>
            <node begin="7" cat="pp" end="13" id="13" rel="mod">
              <node begin="7" end="8" id="14" lemma="in" pos="prep" postag="VZ(init)" pt="vz" rel="hd" root="in" vztype="init" word="in"/>
              <node begin="8" cat="np" end="13" id="15" rel="obj1">
                <node begin="8" end="9" genus="onz" getal="ev" graad="basis" id="16" lemma="artikel" naamval="stan" ntype="soort" pos="noun" postag="N(soort,ev,basis,onz,stan)" pt="n" rel="hd" root="artikel" word="artikel"/>
                <node begin="9" end="10" id="17" lemma="78" numtype="hoofd" pos="num" positie="vrij" postag="TW(hoofd,vrij)" pt="tw" rel="app" root="78" word="78"/>
                <node begin="10" cat="pp" end="13" id="18" rel="mod">
                  <node begin="10" end="11" id="19" lemma="van" pos="prep" postag="VZ(init)" pt="vz" rel="hd" root="van" vztype="init" word="van"/>
                  <node begin="11" cat="np" end="13" id="20" rel="obj1">
                    <node begin="11" end="12" id="21" lemma="de" lwtype="bep" naamval="stan" npagr="rest" pos="det" postag="LID(bep,stan,rest)" pt="lid" rel="det" root="de" word="de"/>
                    <node begin="12" end="13" genus="zijd" getal="ev" graad="basis" id="22" lemma="Grondwet" naamval="stan" ntype="eigen" pos="name" postag="N(eigen,ev,basis,zijd,stan)" pt="n" rel="hd" root="Grondwet" word="Grondwet"/>
                  </node>
                </node>
              </node>
            </node>
          </node>
        </node>
      </node>
    </node>
    <node begin="13" end="14" id="23" lemma="." pos="punct" postag="LET()" pt="let" rel="--" root="." word="."/>
  </node>
  <sentence>Deze wet regelt een aangelegenheid als bedoeld in artikel 78 van de Grondwet .</sentence>
</alpino_ds>
