<?xml version="1.0" encoding="UTF-8"?>
<alpino_ds version="1.3">
  <node begin="0" cat="top" end="14" id="0" rel="top">
    <node begin="0" cat="smain" end="13" id="1" rel="--">
      <node begin="1" end="2" id="2" lemma="zijn" pos="verb" postag="WW(pv,tgw,ev)" pt="ww" pvagr="ev" pvtijd="tgw" rel="hd" root="ben" word="is" wvorm="pv"/>
      <node begin="0" cat="ti" end="13" id="3" rel="vc">
        <node begin="5" end="6" id="4" lemma="te" pos="comp" postag="VZ(init)" pt="vz" rel="cmp" root="te" vztype="init" word="te"/>
        <node begin="0" cat="inf" end="13" id="5" rel="body">
          <node begin="0" end="1" id="6" lemma="ook" pos="adv" postag="BW()" pt="bw" rel="mod" root="ook" word="Ook"/>
          <node begin="2" end="3" getal="getal" id="7" lemma="er" naamval="stan" pdtype="adv-pron" persoon="3" pos="adv" postag="VNW(aanw,adv-pron,stan,red,3,getal)" pt="vnw" rel="mod" root="er" status="red" vwtype="aanw" word="er"/>
          <node begin="6" buiging="zonder" end="7" id="8" lemma="zien" pos="verb" positie="vrij" postag="WW(inf,vrij,zonder)" pt="ww" rel="hd" root="zie" word="zien" wvorm="inf"/>
          <node begin="3" cat="np" end="13" id="9" index="1" rel="obj1">
            <node begin="3" end="4" id="10" lemma="een" lwtype="onbep" naamval="stan" npagr="agr" pos="det" postag="LID(onbep,stan,agr)" pt="lid" rel="det" root="een" word="een"/>
            <node begin="4" end="5" genus="zijd" getal="ev" graad="basis" id="11" lemma="voor_beschouwing" naamval="stan" ntype="soort" pos="noun" postag="N(soort,ev,basis,zijd,stan)" pt="n" rel="hd" root="voor_beschouwing" word="voorbeschouwing"/>
            <node begin="7" cat="pp" end="13" id="12" rel="mod">
              <node begin="7" end="8" id="13" lemma="op" pos="prep" postag="VZ(init)" pt="vz" rel="hd" root="op" vztype="init" word="op"/>
              <node begin="8" cat="np" end="13" id="14" rel="obj1">
                <node begin="8" end="9" id="15" lemma="de" lwtype="bep" naamval="stan" npagr="rest" pos="det" postag="LID(bep,stan,rest)" pt="lid" rel="det" root="de" word="de"/>
                <node begin="9" buiging="met-e" end="10" id="16" lemma="komen" pos="adj" positie="prenom" postag="WW(od,prenom,met-e)" pt="ww" rel="mod" root="kom" word="komende" wvorm="od"/>
                <node begin="10" cat="mwu" end="13" id="17" rel="hd">
                  <node begin="10" end="11" id="18" lemma="Tour" pos="name" postag="SPEC(deeleigen)" pt="spec" rel="mwp" root="Tour" spectype="deeleigen" word="Tour"/>
                  <node begin="11" end="12" id="19" lemma="De" pos="name" postag="SPEC(deeleigen)" pt="spec" rel="mwp" root="De" spectype="deeleigen" word="De"/>
                  <node begin="12" end="13" id="20" lemma="France" pos="name" postag="SPEC(deeleigen)" pt="spec" rel="mwp" root="France" spectype="deeleigen" word="France"/>
                </node>
              </node>
            </node>
          </node>
        </node>
      </node>
      <node begin="3" end="13" id="21" index="1" rel="su"/>
    </node>
    <node begin="13" end="14" id="22" lemma="." pos="punct" postag="LET()" pt="let" rel="--" root="." word="."/>
  </node>
  <sentence>Ook is er een voorbeschouwing te zien op de komende Tour De France .</sentence>
</alpino_ds>
