<?xml version="1.0" encoding="UTF-8"?>
<alpino_ds version="1.3">
  <node begin="0" cat="top" end="4" id="0" rel="top">
    <node begin="1" end="2" id="1" lemma="." pos="punct" postag="LET()" pt="let" rel="--" root="." word="."/>
    <node begin="0" cat="du" end="4" id="2" rel="--">
      <node begin="0" end="1" id="3" lemma="3" numtype="hoofd" pos="tag" positie="vrij" postag="TW(hoofd,vrij)" pt="tw" rel="tag" root="3" word="3"/>
      <node begin="2" cat="inf" end="4" id="4" rel="nucl">
        <node begin="2" end="3" getal="mv" graad="basis" id="5" lemma="contact" ntype="soort" pos="noun" postag="N(soort,mv,basis)" pt="n" rel="obj1" root="contact" word="Contacten"/>
        <node begin="3" buiging="zonder" end="4" id="6" lemma="creëren" pos="verb" positie="vrij" postag="WW(inf,vrij,zonder)" pt="ww" rel="hd" root="creëer" word="creëren" wvorm="inf"/>
      </node>
    </node>
  </node>
  <sentence>3 . Contacten creëren</sentence>
</alpino_ds>
