<?xml version="1.0" encoding="UTF-8"?>
<alpino_ds version="1.3">
  <node begin="0" cat="top" end="4" id="0" rel="top">
    <node begin="0" cat="mwu" end="4" id="1" rel="--">
      <node begin="0" end="1" id="2" lemma="Boulevard" pos="name" postag="SPEC(deeleigen)" pt="spec" rel="mwp" root="boulevard" spectype="deeleigen" word="Boulevard"/>
      <node begin="1" end="2" id="3" lemma="Léopold" pos="name" postag="SPEC(deeleigen)" pt="spec" rel="mwp" root="Léopold" spectype="deeleigen" word="Léopold"/>
      <node begin="2" end="3" id="4" lemma="II" pos="num" postag="SPEC(deeleigen)" pt="spec" rel="mwp" root="II" spectype="deeleigen" word="II"/>
      <node begin="3" end="4" id="5" lemma="44" pos="num" postag="SPEC(deeleigen)" pt="spec" rel="mwp" root="44" spectype="deeleigen" word="44"/>
    </node>
  </node>
  <sentence>Boulevard Léopold II 44</sentence>
</alpino_ds>
