<?xml version="1.0" encoding="UTF-8"?>
<alpino_ds version="1.3">
  <node begin="0" cat="top" end="4" id="0" rel="top">
    <node begin="0" cat="np" end="4" id="1" rel="--">
      <node begin="0" end="1" getal="mv" graad="basis" id="2" lemma="ouder" ntype="soort" pos="noun" postag="N(soort,mv,basis)" pt="n" rel="hd" root="ouder" word="Ouders"/>
      <node begin="1" cat="pp" end="4" id="3" rel="mod">
        <node begin="1" end="2" id="4" lemma="zonder" pos="prep" postag="VZ(init)" pt="vz" rel="hd" root="zonder" vztype="init" word="zonder"/>
        <node begin="2" cat="np" end="4" id="5" rel="obj1">
          <node begin="2" buiging="met-e" end="3" graad="basis" id="6" lemma="vast" naamval="stan" pos="adj" positie="prenom" postag="ADJ(prenom,basis,met-e,stan)" pt="adj" rel="mod" root="vast" word="vaste"/>
          <node begin="3" end="4" genus="zijd" getal="ev" graad="basis" id="7" lemma="woon_plaats" naamval="stan" ntype="soort" pos="noun" postag="N(soort,ev,basis,zijd,stan)" pt="n" rel="hd" root="woon_plaats" word="woonplaats"/>
        </node>
      </node>
    </node>
  </node>
  <sentence>Ouders zonder vaste woonplaats</sentence>
</alpino_ds>
