<?xml version="1.0" encoding="UTF-8"?>
<alpino_ds version="1.3">
  <node begin="0" cat="top" end="5" id="0" rel="top">
    <node begin="0" end="1" id="1" lemma="-" pos="punct" postag="LET()" pt="let" rel="--" root="-" word="-"/>
    <node begin="1" cat="np" end="4" id="2" rel="--">
      <node begin="1" end="2" getal="mv" graad="basis" id="3" lemma="sensibilisering_campagne" ntype="soort" pos="name" postag="N(soort,mv,basis)" pt="n" rel="hd" root="Sensibiliseringscampagnes" word="Sensibiliseringscampagnes"/>
      <node begin="2" cat="rel" end="4" id="4" rel="mod">
        <node begin="2" end="3" getal="getal" id="5" lemma="waar" naamval="obl" pdtype="adv-pron" persoon="3o" pos="adv" postag="VNW(vb,adv-pron,obl,vol,3o,getal)" pt="vnw" rel="rhd" root="waar" status="vol" vwtype="vb" word="waar"/>
        <node begin="3" buiging="zonder" end="4" graad="basis" id="6" lemma="nodig" pos="adj" positie="vrij" postag="ADJ(vrij,basis,zonder)" pt="adj" rel="body" root="nodig" word="nodig"/>
      </node>
    </node>
    <node begin="4" end="5" id="7" lemma="." pos="punct" postag="LET()" pt="let" rel="--" root="." word="."/>
  </node>
  <sentence>- Sensibiliseringscampagnes waar nodig .</sentence>
</alpino_ds>
